dag_dataset/__init__.py
dag_dataset/config_reader.py
dag_dataset/constants.py
dag_dataset/data_objects.py
dag_dataset/dataset.py
dag_dataset/examples.py
dag_dataset/test_table.csv
dag_dataset/validator.py
dag_dataset-0.1.1.dist-info/METADATA
dag_dataset-0.1.1.dist-info/WHEEL
dag_dataset-0.1.1.dist-info/licenses/LICENSE
dag_dataset-0.1.1.dist-info/RECORD
